{
  "slug": "adore-cacupe",
  "padrao": "alto",
  "ac_m2": 6494.63,
  "ur": 46,
  "n_pavimentos": 8,
  "n_torres": 0,
  "total_r$": 0,
  "data_extracao": "2026-04-17T20:03:49",
  "duration_s": 0.0,
  "n_itens_processados": 184,
  "n_itens_classificados": 184,
  "n_indicadores_extraidos": 18,
  "indicadores": {
    "cobertura_m2_por_m2_ac": {
      "id": "DIV_05",
      "valor": 0.2353,
      "unidade": "m²/m² AC",
      "soma_bruta": 1528.16,
      "n_itens": 6,
      "itens_fonte": [
        "NÍVEL 7 - (PAVCOBERTURA)",
        "COBERTURA",
        "Cobertura para proteção de pedestres",
        "Cobertura para proteção de pedestres",
        "Estrutura de Madeira para Telhado",
        "Telha Fibrocimento 8mm"
      ]
    },
    "alvenaria_m2_por_m2_ac": {
      "id": "ALV_01",
      "valor": 2.2231,
      "unidade": "m²/m² AC",
      "soma_bruta": 14438.5,
      "n_itens": 6,
      "itens_fonte": [
        "ALVENARIA",
        "Alvenaria de vedacao de blocos ceramicos furados na horizontal de 9x19x29cm (esp",
        "Alvenaria de vedacao de blocos ceramicos furados na horizontal de 11.5x19x29cm (",
        "Alvenaria de vedacao de blocos ceramicos furados na horizontal de 14x19x29cm (es",
        "Alvenaria refratárias",
        "Encunhamento para alvenaria de vedação com argamassa expansiva"
      ]
    },
    "aco_kg_por_m2_ac": {
      "id": "EST_02",
      "valor": 21.8357,
      "unidade": "kg/m² AC",
      "soma_bruta": 141814.51,
      "n_itens": 12,
      "itens_fonte": [
        "INSTALAÇÕES ELÉTRICAS, HIDRÁULICAS, GLP E PREVENTIVAS",
        "ACABAMENTOS EM PISOS E PAVIMENTAÇÕES",
        "Varal de seguranca com cabo de aco com cabo de aço instalado junto ao piso",
        "Fabricação, montagem e desmontagem de forma para blocos e baldrames em madeira s",
        "Armação",
        "Armação",
        "Fabricação forma (vigas, pilares e escadas) em madeira serrada (2 utilizações)",
        "Fabricação forma lajes em madeirite 17mm (3 utilizações)",
        "Tela soldada para ligação alvenaria/estrutura",
        "Proteção mecânica com argamassa de cimento e areia, traço 1:3, espessura 5 cm, c"
      ]
    },
    "manta_asfaltica_m2_por_m2_ac": {
      "id": "IMP_01",
      "valor": 2.1151,
      "unidade": "m²/m² AC",
      "soma_bruta": 13736.51,
      "n_itens": 7,
      "itens_fonte": [
        "IMPERMEABILIZAÇÃO",
        "Regularização de superfície para impermeabilização",
        "Impermeabilização de baldrames com tinta asfáltica",
        "Impermeabilização com manta asfáltica",
        "Impermeabilização com argamassa polimérica",
        "Impermeabilização Poço do Elevador",
        "Mão de obra para impermeabilização de poço e baldrames"
      ]
    },
    "pintura_interna_m2_por_m2_ac": {
      "id": "PIN_01",
      "valor": 2.8847,
      "unidade": "m²/m² AC",
      "soma_bruta": 18734.81,
      "n_itens": 4,
      "itens_fonte": [
        "PINTURA INTERNA",
        "Pintura piso resina acrílica",
        "Pintura parede (selador + massa + pintura)",
        "Pintura teto (selador + massa + pintura)"
      ]
    },
    "vidros_m2_por_m2_ac": {
      "id": "ESQ_03",
      "valor": 0.0503,
      "unidade": "m²/m² AC",
      "soma_bruta": 326.52,
      "n_itens": 2,
      "itens_fonte": [
        "ESQUADRIAS, VIDROS E FERRAGENS",
        "Guarda-corpo - vidro"
      ]
    },
    "portas_un_por_ur": {
      "id": "ESQ_01",
      "valor": 2.9633,
      "unidade": "un/UR",
      "soma_bruta": 136.31,
      "n_itens": 5,
      "itens_fonte": [
        "Área das portas de elevadores",
        "Área das portas de aptos",
        "Fechamento removível de vãos de porta de entrada dos aptos. em madeira",
        "Fechamento removivel de vaos de porta de elevador em madeira",
        "Moldura porta elevador (pedra natural)"
      ]
    },
    "elevadores_por_torre": {
      "id": "DIV_02",
      "valor": 10.0,
      "unidade": "un/torre",
      "soma_bruta": 10.0,
      "n_itens": 3,
      "itens_fonte": [
        "Quantidade de elevadores",
        "Quantidade de pavimentos de elevadores",
        "Elevadores"
      ]
    },
    "concreto_m3_por_m2_ac": {
      "id": "EST_01",
      "valor": 0.1408,
      "unidade": "m³/m² AC",
      "soma_bruta": 914.47,
      "n_itens": 1,
      "itens_fonte": [
        "Lastro de concreto magro"
      ]
    },
    "escoramento_m2_por_m2_ac": {
      "id": "EST_04",
      "valor": 0.8163,
      "unidade": "m²/m² AC",
      "soma_bruta": 5301.35,
      "n_itens": 1,
      "itens_fonte": [
        "Escoramento (pontalete de madeira)"
      ]
    },
    "chapisco_m2_por_m2_ac": {
      "id": "REV_01",
      "valor": 3.3857,
      "unidade": "m²/m² AC",
      "soma_bruta": 21988.97,
      "n_itens": 2,
      "itens_fonte": [
        "Chapisco rolado",
        "Chapisco e reboco"
      ]
    },
    "reboco_m2_por_m2_ac": {
      "id": "REV_02",
      "valor": 2.2834,
      "unidade": "m²/m² AC",
      "soma_bruta": 14829.85,
      "n_itens": 1,
      "itens_fonte": [
        "Massa unica para reboco interno em argamassa estabilizada"
      ]
    },
    "forro_gesso_m2_por_m2_ac": {
      "id": "DIV_01",
      "valor": 0.2061,
      "unidade": "m²/m² AC",
      "soma_bruta": 1338.78,
      "n_itens": 2,
      "itens_fonte": [
        "Forro de gesso acartonado - material e mão de obra",
        "Forro de madeira de lei - material  mão de obra"
      ]
    },
    "contrapiso_m2_por_m2_ac": {
      "id": "REV_03",
      "valor": 1.0769,
      "unidade": "m²/m² AC",
      "soma_bruta": 6994.15,
      "n_itens": 1,
      "itens_fonte": [
        "Contrapiso convencional com argamassa usinada"
      ]
    },
    "porcelanato_ceramica_m2_por_m2_ac": {
      "id": "REV_04",
      "valor": 0.6122,
      "unidade": "m²/m² AC",
      "soma_bruta": 3976.25,
      "n_itens": 2,
      "itens_fonte": [
        "Porcelanato",
        "Pastilha cerâmica"
      ]
    },
    "guarda_corpo_m_por_m2_ac": {
      "id": "ESQ_04",
      "valor": 0.078,
      "unidade": "m/m² AC",
      "soma_bruta": 506.87,
      "n_itens": 3,
      "itens_fonte": [
        "Guarda-corpo - alumínio",
        "Corrimão de Alumínio escadas Anti-incêndio",
        "Corrimão de Alumínio escadas Anti-incêndio"
      ]
    },
    "pintura_externa_m2_por_m2_ac": {
      "id": "PIN_02",
      "valor": 2.3207,
      "unidade": "m²/m² AC",
      "soma_bruta": 15071.83,
      "n_itens": 2,
      "itens_fonte": [
        "Pintura externa",
        "Textura externa"
      ]
    },
    "taxa_aco_kg_por_m3": {
      "id": "EST_03b",
      "valor": 155.08,
      "unidade": "kg/m³",
      "soma_bruta": 141814.5089668107,
      "n_itens": 12,
      "itens_fonte": [
        "(calculado: aço total / concreto total)"
      ]
    }
  },
  "nao_classificados_sample": [
    "MESES DE OBRA",
    "ÁREA DO TERRENO",
    "ÁREA CONSTRUÍDA",
    "NÚMERO DE UNIDADES HABITACIONAIS",
    "NÚMERO DE UNIDADES COMERCIAIS",
    "ÁREA PRIVATIVA",
    "ÁREA COMERCIAL",
    "NÚMERO DE PAVIMENTOS",
    "NÍVEL 1 - (PAV.01 e PAV. SUBSOLO 02)",
    "NÍVEL 2 - (SL/MEZ e PAV. SUBSOLO 01)",
    "NÍVEL 3 - (PAV02 e PAV01)",
    "NÍVEL 4 - (PAV03 e PAV02)",
    "NÍVEL 5 - (PAV04 e PAV03)",
    "NÍVEL 6 - (PAV05 e PAV04)",
    "RESERVATÓRIOS",
    "ÁREA COMERCIAL",
    "NUMERO DE VAGAS RESIDENCIAIS",
    "NUMERO DE VAGAS COMERCIAIS",
    "NÚMERO DE VAGAS BICICLETÁRIO",
    "MOVIMENTAÇÃO DE TERRA"
  ]
}