{
  "slug_parametrico": "thozen-electra",
  "slug_executivo": "thozen-mirador-de-alicante",
  "data": "2026-04-18T08:24:46",
  "parametrico": {
    "total_r$": 157477533.37,
    "rsm2": 4155.75,
    "ac": 37893.89,
    "padrao": "alto"
  },
  "executivo": {
    "total_r$": 35031764.70723375,
    "rsm2": 73777.86906632235,
    "ac": 474.8275485666585
  },
  "delta_total_r$": -122445768.66,
  "delta_total_pct": -77.8,
  "diagnostico": "FORA DA FAIXA (>20%)",
  "comparacao_por_mg": [
    {
      "macrogrupo": "Cobertura",
      "parametrico_r$": 0,
      "executivo_r$": 143854.05,
      "delta_r$": 143854.05,
      "delta_pct": null
    },
    {
      "macrogrupo": "Esquadrias",
      "parametrico_r$": 0,
      "executivo_r$": 2218820.63,
      "delta_r$": 2218820.63,
      "delta_pct": null
    },
    {
      "macrogrupo": "Fachada",
      "parametrico_r$": 0,
      "executivo_r$": 1586316.14,
      "delta_r$": 1586316.14,
      "delta_pct": null
    },
    {
      "macrogrupo": "Gerenciamento",
      "parametrico_r$": 0,
      "executivo_r$": 5062193.47,
      "delta_r$": 5062193.47,
      "delta_pct": null
    },
    {
      "macrogrupo": "Impermeabilizacao",
      "parametrico_r$": 0,
      "executivo_r$": 441429.8,
      "delta_r$": 441429.8,
      "delta_pct": null
    },
    {
      "macrogrupo": "Infraestrutura",
      "parametrico_r$": 0,
      "executivo_r$": 2848541.68,
      "delta_r$": 2848541.68,
      "delta_pct": null
    },
    {
      "macrogrupo": "Instalacoes Hidrossanitarias",
      "parametrico_r$": 0,
      "executivo_r$": 2908684.79,
      "delta_r$": 2908684.79,
      "delta_pct": null
    },
    {
      "macrogrupo": "Loucas e Metais",
      "parametrico_r$": 0,
      "executivo_r$": 325261.7,
      "delta_r$": 325261.7,
      "delta_pct": null
    },
    {
      "macrogrupo": "Outros",
      "parametrico_r$": 0,
      "executivo_r$": 3599316.62,
      "delta_r$": 3599316.62,
      "delta_pct": null
    },
    {
      "macrogrupo": "Pintura Interna",
      "parametrico_r$": 0,
      "executivo_r$": 1891027.32,
      "delta_r$": 1891027.32,
      "delta_pct": null
    },
    {
      "macrogrupo": "Pisos e Pavimentacoes",
      "parametrico_r$": 0,
      "executivo_r$": 1103823.65,
      "delta_r$": 1103823.65,
      "delta_pct": null
    },
    {
      "macrogrupo": "Revestimentos Parede",
      "parametrico_r$": 0,
      "executivo_r$": 483917.52,
      "delta_r$": 483917.52,
      "delta_pct": null
    },
    {
      "macrogrupo": "Revestimentos Teto",
      "parametrico_r$": 0,
      "executivo_r$": 495265.23,
      "delta_r$": 495265.23,
      "delta_pct": null
    },
    {
      "macrogrupo": "Servicos Complementares",
      "parametrico_r$": 0,
      "executivo_r$": 1286345.38,
      "delta_r$": 1286345.38,
      "delta_pct": null
    },
    {
      "macrogrupo": "Sistemas Especiais",
      "parametrico_r$": 0,
      "executivo_r$": 2076277.77,
      "delta_r$": 2076277.77,
      "delta_pct": null
    },
    {
      "macrogrupo": "Supraestrutura",
      "parametrico_r$": 0,
      "executivo_r$": 8560688.95,
      "delta_r$": 8560688.95,
      "delta_pct": null
    }
  ]
}