{
  "slug": "inbrasul-opus",
  "cliente_inferido": "inbrasul",
  "padrao": "medio-alto",
  "tipologia_gemma": null,
  "cidade": "Navegantes",
  "uf": "SC",
  "cub_regiao": "SC-Vale-Itajai",
  "ac_m2": 4410.5,
  "ur": 36,
  "total_rs": 16756730.41,
  "rsm2": 3799.28,
  "concreto_m3_m2_ac": null,
  "taxa_aco_kg_m3": null,
  "forma_m2_m2_ac": null,
  "fck_predominante": null,
  "sistema_estrutural": null,
  "n_pavimentos_total": null,
  "n_pavimentos_garagem": null,
  "n_pavimentos_tipo": null,
  "n_torres": null,
  "n_elevadores": null,
  "n_tipologias_apto": null,
  "area_privativa_tipo_m2": null,
  "tem_pele_vidro": null,
  "tem_piscina": null,
  "tem_gerador": null,
  "tem_spda": null,
  "tem_climatizacao_central": null,
  "tem_churrasqueira_apto": null,
  "tem_subsolo": null,
  "tem_metadados_gemma": true,
  "observacoes_gemma": "Orcamento Resumo. Sem Imprevistos.",
  "cub_referencia_memorial": null,
  "data_memorial": "2022-12-01",
  "data_base": "2022-02",
  "data_base_fonte": "ground_truth_entrega",
  "cidade_fonte": "ground_truth_entrega",
  "tipologia_canonica": "residencial_vertical_medio_alto",
  "tipologia_confianca": "alta"
}